MANIFEST.in
setup.py
django_g_recaptcha.egg-info/PKG-INFO
django_g_recaptcha.egg-info/SOURCES.txt
django_g_recaptcha.egg-info/dependency_links.txt
django_g_recaptcha.egg-info/requires.txt
django_g_recaptcha.egg-info/top_level.txt
g_recaptcha/.DS_Store
g_recaptcha/__init__.py
g_recaptcha/__init__.pyc
g_recaptcha/models.py
g_recaptcha/models.pyc
g_recaptcha/tests.py
g_recaptcha/tests.pyc
g_recaptcha/validate_recaptcha.py
g_recaptcha/validate_recaptcha.pyc
g_recaptcha/views.py
g_recaptcha/templates/captcha_fail.html