Metadata-Version: 1.0
Name: django-g-recaptcha
Version: 0.2.1
Summary: Django view decorator to validate google recaptcha forms
Home-page: https://github.com/deltaskelta/django-g-recaptcha
Author: Jeff Willette
Author-email: jrwillette88@gmail.com
License: UNKNOWN
Keywords: django,recaptcha,catpcha,google
Platform: UNKNOWN
